Metadata-Version: 2.4
Name: ugbio_filtering
Version: 1.20.0
Summary: Ultima Genomics filtering scripts
Author-email: Ilya Soifer <ilya.soifer@ultimagen.com>, Doron Shem-Tov <doron.shemtov@ultimagen.com>, Avigail Moldovan <avigail.moldovan@ultimagen.com>
License: Apache-2.0
Requires-Python: >=3.11
Requires-Dist: ugbio_comparison
Requires-Dist: pickle-secure>=0.99.9
Requires-Dist: dill>=0.3.9
